constants.py
example.py
file_wrapper.py
headers.py
jdcloud_wsgi_wrapper.py
setup.py
jdcloud_wsgi_wrapper.egg-info/PKG-INFO
jdcloud_wsgi_wrapper.egg-info/SOURCES.txt
jdcloud_wsgi_wrapper.egg-info/dependency_links.txt
jdcloud_wsgi_wrapper.egg-info/top_level.txt