Metadata-Version: 1.0
Name: jdcloud-wsgi-wrapper
Version: 1.3
Summary: jdcloud wsgi wrapper
Home-page: https://github.com/binju2197/jdcloud-wsgi-wrapper
Author: function
Author-email: UNKNOWN
License: UNKNOWN
Platform: UNKNOWN
